simplebitk/__init__.py
simplebitk/_nbdev.py
simplebitk/defaults.py
simplebitk/nanopore.py
simplebitk/pipelines.py
simplebitk/plots.py
simplebitk/preprocess.py
simplebitk/run_all.py
simplebitk/bam/__init__.py
simplebitk/bam/reads.py
simplebitk/merge/__init__.py
simplebitk/merge/degfc.py
simplebitk/utils/__init__.py
simplebitk/utils/bamfilter.py
simplebitk/utils/clusters.py
simplebitk/utils/dedimensions.py
simplebitk/utils/multirun.py
simplebitk/utils/plots.py
simplebitk-0.0.1a0.dist-info/LICENSE
simplebitk-0.0.1a0.dist-info/METADATA
simplebitk-0.0.1a0.dist-info/WHEEL
simplebitk-0.0.1a0.dist-info/entry_points.txt
simplebitk-0.0.1a0.dist-info/top_level.txt
simplebitk-0.0.1a0.dist-info/RECORD
