Metadata-Version: 2.1
Name: simplebitk
Version: 0.0.1a0
Summary: A bioinformatics tools kit
Home-page: https://github.com/btrspg/simplebitk/tree/master/
Author: Yuelong CHEN
Author-email: yuelong.chen.btr@gmail.com
License: Apache Software License 2.0
Keywords: biology bioinformatics
Platform: UNKNOWN
Classifier: Development Status :: 2 - Pre-Alpha
Classifier: Intended Audience :: Developers
Classifier: License :: OSI Approved :: Apache Software License
Classifier: Natural Language :: English
Classifier: Programming Language :: Python :: 3.6
Classifier: Programming Language :: Python :: 3.7
Classifier: Programming Language :: Python :: 3.8
Requires-Python: >=3.6
Requires-Dist: scikit-learn
Requires-Dist: phate
Requires-Dist: umap-learn
Requires-Dist: scipy
Requires-Dist: seaborn
Requires-Dist: defopt
Requires-Dist: pysam
